{
  "$schema": "https://raw.githubusercontent.com/iconmaster5326/YGOJSON/main/schema/v1/card.json",
  "id": "21fbd28d-b7c8-4b1c-8419-6e3f8cdba573",
  "text": {
    "en": {
      "name": "Exosister Karmael",
      "effect": "2 Level 4 \"Exosister\" monsters\nIf this card is Xyz Summoned: You can activate this effect; during the End Phase of this turn, Set 1 \"Exosister\" Spell/Trap from your Deck, GY, or banishment. When your opponent activates a monster effect or a Normal Spell/Trap Card (Quick Effect): You can detach all materials from this card, and if you do, the activated effect becomes \"Add 1 card from your opponent's GY to their hand\". You can only use each effect of \"Exosister Karmael\" once per turn.",
      "official": false
    },
    "ja": {
      "name": "\u30a8\u30af\u30bd\u30b7\u30b9\u30bf\u30fc\u30fb\u30ab\u30eb\u30de\u30a8\u30eb",
      "effect": "\u30ec\u30d9\u30eb\uff14\u300c\u30a8\u30af\u30bd\u30b7\u30b9\u30bf\u30fc\u300d\u30e2\u30f3\u30b9\u30bf\u30fc\u00d7\uff12\n\u3053\u306e\u30ab\u30fc\u30c9\u540d\u306e\u2460\u2461\u306e\u52b9\u679c\u306f\u305d\u308c\u305e\u308c\uff11\u30bf\u30fc\u30f3\u306b\uff11\u5ea6\u3057\u304b\u4f7f\u7528\u3067\u304d\u306a\u3044\u3002\u2460\uff1a\u3053\u306e\u30ab\u30fc\u30c9\u304c\uff38\u53ec\u559a\u3057\u305f\u5834\u5408\u306b\u767a\u52d5\u3067\u304d\u308b\u3002\u3053\u306e\u30bf\u30fc\u30f3\u306e\u30a8\u30f3\u30c9\u30d5\u30a7\u30a4\u30ba\u306b\u3001\u81ea\u5206\u306e\u30c7\u30c3\u30ad\u30fb\u5893\u5730\u30fb\u9664\u5916\u72b6\u614b\u306e\u300c\u30a8\u30af\u30bd\u30b7\u30b9\u30bf\u30fc\u300d\u9b54\u6cd5\u30fb\u7f60\u30ab\u30fc\u30c9\uff11\u679a\u3092\u81ea\u5206\u30d5\u30a3\u30fc\u30eb\u30c9\u306b\u30bb\u30c3\u30c8\u3059\u308b\u3002\u2461\uff1a\u76f8\u624b\u304c\u30e2\u30f3\u30b9\u30bf\u30fc\u306e\u52b9\u679c\u30fb\u901a\u5e38\u9b54\u6cd5\u30fb\u901a\u5e38\u7f60\u30ab\u30fc\u30c9\u3092\u767a\u52d5\u3057\u305f\u6642\u306b\u767a\u52d5\u3067\u304d\u308b\u3002\u3053\u306e\u30ab\u30fc\u30c9\u306e\uff38\u7d20\u6750\u3092\u5168\u3066\u53d6\u308a\u9664\u304d\u3001\u305d\u306e\u52b9\u679c\u306f\u300c\u76f8\u624b\u306e\u5893\u5730\u304b\u3089\u30ab\u30fc\u30c9\uff11\u679a\u3092\u76f8\u624b\u306e\u624b\u672d\u306b\u52a0\u3048\u308b\u300d\u3068\u306a\u308b\u3002"
    },
    "zh-CN": {
      "name": "\u9a71\u9b54\u59d0\u59b9\u30fb\u5361\u5c14\u739b\u5c14"
    }
  },
  "cardType": "monster",
  "attribute": "dark",
  "monsterCardTypes": [
    "xyz"
  ],
  "type": "fairy",
  "classifications": [
    "effect"
  ],
  "rank": 4,
  "atk": 2600,
  "def": 1800,
  "passwords": [
    "77675029"
  ],
  "images": [
    {
      "id": "122e29e6-2de4-4373-b056-98d6dbd3ffcd",
      "art": "https://images.ygoprodeck.com/images/cards_cropped/101303044.jpg",
      "card": "https://images.ygoprodeck.com/images/cards/101303044.jpg"
    },
    {
      "id": "ad6c4e3b-8ed7-4ab2-bfe7-b1e25a9f2abd",
      "password": "77675029",
      "art": "https://images.ygoprodeck.com/images/cards_cropped/77675029.jpg",
      "card": "https://images.ygoprodeck.com/images/cards/77675029.jpg"
    }
  ],
  "sets": [
    "f57caed9-b5dd-41bb-8752-d17f13f0feda",
    "f57caed9-b5dd-41bb-8752-d17f13f0feda",
    "f57caed9-b5dd-41bb-8752-d17f13f0feda"
  ],
  "legality": {},
  "externalIDs": {
    "yugipedia": [
      {
        "name": "Exosister Karmael",
        "id": 1153491
      }
    ],
    "dbID": 22147,
    "ygoprodeck": {
      "id": 77675029,
      "name": "exosister-karmael-15367"
    }
  },
  "series": [
    "e9919a86-6b2b-4024-9bb8-5a8f25582dd8"
  ]
}