{
  "$schema": "https://raw.githubusercontent.com/iconmaster5326/YGOJSON/main/schema/v1/card.json",
  "id": "3872b2e0-e3f8-4986-99f7-c31fe2ac4807",
  "text": {
    "en": {
      "name": "B. Dragon Jungle King",
      "official": false
    },
    "de": {
      "name": "Schw. Drachen-Dschungelk\u00f6nig",
      "effect": "Ein schwarzer Drache, der in den tiefsten Urw\u00e4ldern zu finden ist und normalerweise B\u00e4ume verschlingt."
    },
    "es": {
      "name": "B. el rey de selva de drag\u00f3n",
      "effect": "Un drag\u00f3n negro azabache que se encuentra en las junglas m\u00e1s tupidas y que normalmente devora \u00e1rboles."
    },
    "fr": {
      "name": "Dragon, Roi de la jungle",
      "effect": "Dragon noir comme le jais qui vit dans les jungles les plus recul\u00e9es et qui engloutit des arbres entiers."
    },
    "it": {
      "name": "Drago Re della Giungla",
      "effect": "Questo drago nero-lucente \u00e8 un abitante delle giungle e un grande divoratore di alberi."
    },
    "pt": {
      "name": "Drag\u00e3o Negro Rei da Selva",
      "effect": "Um drag\u00e3o negro encontrado nas mais profundas florestas e que normalmente devora \u00e1rvores."
    },
    "ja": {
      "name": "\u5bc6\u6797\u306e\u9ed2\u7adc\u738b",
      "effect": "\u5bc6\u6797\u306b\u751f\u606f\u3059\u308b\u3001\u6f06\u9ed2\u306e\u30c9\u30e9\u30b4\u30f3\u3002\u30d0\u30ea\u30d0\u30ea\u3068\u6728\u3092\u98df\u3079\u308b\u3002"
    },
    "ko": {
      "name": "\ubc00\ub9bc\uc758 \ud751\ub8e1\uc655",
      "effect": "\ubc00\ub9bc\uc5d0\uc11c \uc0dd\uc2dd\ud558\ub294 \uce60\ud751\uc758 \ub4dc\ub798\uace4. \uc73c\ub4dc\ub4dd\uc73c\ub4dc\ub4dd \ub098\ubb34\ub97c \uba39\ub294\ub2e4."
    },
    "zh-TW": {
      "name": "\u5bc6\u6797\u7684\u9ed1\u9f8d\u738b",
      "effect": "\u68f2\u606f\u65bc\u5bc6\u6797\u4e2d\u7684\u6f06\u9ed1\u9f8d\u3002\u6703\u5927\u53e3\u628a\u6a39\u5403\u6389\u3002"
    },
    "zh-CN": {
      "name": "\u5bc6\u6797\u7684\u9ed1\u9f99\u738b",
      "effect": "\u6816\u606f\u5728\u5bc6\u6797\u6df1\u5904\u7684\u6f06\u9ed1\u9f99\u738b\u3002\u54af\u5431\u54af\u5431\u7684\u53ea\u77e5\u9053\u5543\u98df\u6811\u6728\u3002"
    }
  },
  "cardType": "monster",
  "attribute": "earth",
  "type": "dragon",
  "classifications": [
    "normal"
  ],
  "level": 6,
  "atk": 2100,
  "def": 1800,
  "passwords": [
    "89832901"
  ],
  "images": [
    {
      "id": "b006cb85-f176-4378-ba09-9ebf08059b29",
      "password": "89832901",
      "art": "https://images.ygoprodeck.com/images/cards_cropped/89832901.jpg",
      "card": "https://images.ygoprodeck.com/images/cards/89832901.jpg"
    }
  ],
  "sets": [
    "52f58790-1cf8-4fa3-a35f-a2aee2c1daa2",
    "13444ca5-be50-49b2-a2db-ee3f5cba7e64",
    "afd7ca9a-b582-4135-a42a-55b1d854fde7"
  ],
  "legality": {
    "ocg": {
      "current": "unlimited"
    }
  },
  "masterDuel": {
    "rarity": "n",
    "craftable": true
  },
  "duelLinks": {
    "rarity": "n"
  },
  "externalIDs": {
    "yugipedia": [
      {
        "name": "B. Dragon Jungle King",
        "id": 18841
      }
    ],
    "dbID": 4577,
    "ygoprodeck": {
      "id": 89832901,
      "name": "b-dragon-jungle-king-7507"
    },
    "yamlyugiID": 89832901
  },
  "series": [
    "bdb6fa9e-a4fb-4017-827d-56a444e55320"
  ]
}