{
  "$schema": "https://raw.githubusercontent.com/iconmaster5326/YGOJSON/main/schema/v1/card.json",
  "id": "78bf3bf7-bcce-4590-9fda-8f0299d44ddf",
  "text": {
    "en": {
      "name": "Gusto Gulldo",
      "effect": "When this card is sent from the field to the Graveyard: You can Special Summon 1 Level 2 or lower \"Gusto\" monster from your Deck."
    },
    "de": {
      "name": "Gusto Gulldo",
      "effect": "Wenn diese Karte vom Spielfeld auf den Friedhof gelegt wird: Du kannst 1 \"Gusto\"-Monster der Stufe 2 oder niedriger als Spezialbeschw\u00f6rung von deinem Deck beschw\u00f6ren."
    },
    "es": {
      "name": "Gusto Gulldo",
      "effect": "Cuando esta carta es mandada del Campo al Cementerio: puedes Invocar de Modo Especial, desde tu Deck, 1 monstruo \"Gusto\" de Nivel 2 o menor."
    },
    "fr": {
      "name": "Gusto Gulldo",
      "effect": "Lorsque cette carte est envoy\u00e9e depuis le Terrain au Cimeti\u00e8re : vous pouvez Invoquer Sp\u00e9cialement 1 monstre \"Gusto\" de max. Niveau 2 depuis votre Deck."
    },
    "it": {
      "name": "Gusto Gulldo",
      "effect": "Quando questa carta viene mandata dal Terreno al Cimitero: puoi Evocare Specialmente 1 mostro \"Gusto\" di Livello 2 o inferiore dal tuo Deck."
    },
    "pt": {
      "name": "Gulldo Gusto",
      "effect": "Quando este card for enviado do campo para o Cemit\u00e9rio: Voc\u00ea pode Invocar por Invoca\u00e7\u00e3o-Especial 1 monstro \"Gusto\" de N\u00edvel 2 ou menos do seu Deck."
    },
    "ja": {
      "name": "\u30ac\u30b9\u30bf\u30fb\u30ac\u30eb\u30c9",
      "effect": "\u3053\u306e\u30ab\u30fc\u30c9\u304c\u30d5\u30a3\u30fc\u30eb\u30c9\u4e0a\u304b\u3089\u5893\u5730\u3078\u9001\u3089\u308c\u305f\u6642\u3001\u81ea\u5206\u306e\u30c7\u30c3\u30ad\u304b\u3089\u30ec\u30d9\u30eb\uff12\u4ee5\u4e0b\u306e\u300c\u30ac\u30b9\u30bf\u300d\u3068\u540d\u306e\u3064\u3044\u305f\u30e2\u30f3\u30b9\u30bf\u30fc\uff11\u4f53\u3092\u7279\u6b8a\u53ec\u559a\u3059\u308b\u4e8b\u304c\u3067\u304d\u308b\u3002"
    },
    "ko": {
      "name": "\uac00\uc2a4\ud0c0 \uac00\ub974\ub3c4",
      "effect": "\uc774 \uce74\ub4dc\uac00 \ud544\ub4dc \uc704\uc5d0\uc11c \ubb18\uc9c0\ub85c \ubcf4\ub0b4\uc84c\uc744 \ub54c, \uc790\uc2e0\uc758 \ub371\uc5d0\uc11c \ub808\ubca8 2 \uc774\ud558\uc758 '\uac00\uc2a4\ud0c0' \ub77c\ub294 \uc774\ub984\uc774 \ubd99\uc740 \ubaac\uc2a4\ud130 1\uc7a5\uc744 \ud2b9\uc218 \uc18c\ud658\ud560 \uc218 \uc788\ub2e4."
    },
    "zh-TW": {
      "name": "\u85b0\u98a8\u30fb\u9d6c",
      "effect": "\u53ef\u5728\u6b64\u5361\u5f9e\u5834\u4e0a\u88ab\u9001\u81f3\u5893\u5730\u6642\u767c\u52d5\u3002\u5f9e\u724c\u7d44\u7279\u6b8a\u53ec\u559a\uff11\u96bb\u7b49\u7d1a\uff12\u4ee5\u4e0b\u7684\u51a0\u6709\u300c\u85b0\u98a8\u300d\u4e4b\u540d\u7684\u602a\u7378\u3002"
    },
    "zh-CN": {
      "name": "\u85b0\u98ce\u9e4f",
      "effect": "\u8fd9\u5f20\u5361\u4ece\u573a\u4e0a\u9001\u53bb\u5893\u5730\u65f6\uff0c\u53ef\u4ee5\u4ece\u5361\u7ec4\u628a1\u53ea2\u661f\u4ee5\u4e0b\u7684\u540d\u5b57\u5e26\u6709\u300c\u85b0\u98ce\u300d\u7684\u602a\u517d\u7279\u6b8a\u53ec\u5524\u3002"
    }
  },
  "cardType": "monster",
  "attribute": "wind",
  "type": "wingedbeast",
  "classifications": [
    "tuner"
  ],
  "level": 3,
  "atk": 500,
  "def": 500,
  "passwords": [
    "65277087"
  ],
  "images": [
    {
      "id": "4650e133-3b0b-45de-b6be-ef4682ee60f9",
      "password": "65277087",
      "art": "https://images.ygoprodeck.com/images/cards_cropped/65277087.jpg",
      "card": "https://images.ygoprodeck.com/images/cards/65277087.jpg"
    }
  ],
  "sets": [
    "f96dde07-f28c-430b-8a49-d65ac06872e1",
    "f96dde07-f28c-430b-8a49-d65ac06872e1",
    "f96dde07-f28c-430b-8a49-d65ac06872e1",
    "f96dde07-f28c-430b-8a49-d65ac06872e1",
    "f96dde07-f28c-430b-8a49-d65ac06872e1",
    "f96dde07-f28c-430b-8a49-d65ac06872e1",
    "c793d3b3-c850-4012-bf11-a3c755b57024",
    "70093d2b-85e3-4680-bf00-ec392f803db3",
    "22566ca5-5463-419d-a81e-ae5562364c7e",
    "961f3a82-9074-4e09-8237-a0a84d3a6b69",
    "ffbfa020-b79b-4f2a-b399-7061b868525f",
    "7a237401-5618-4633-afe9-5d5e686e5a2a"
  ],
  "legality": {
    "tcg": {
      "current": "unlimited"
    },
    "ocg": {
      "current": "unlimited"
    }
  },
  "masterDuel": {
    "rarity": "n",
    "craftable": true
  },
  "duelLinks": {
    "rarity": "r"
  },
  "externalIDs": {
    "yugipedia": [
      {
        "name": "Gusto Gulldo",
        "id": 141788
      }
    ],
    "dbID": 9164,
    "ygoprodeck": {
      "id": 65277087,
      "name": "gusto-gulldo-5500"
    },
    "yamlyugiID": 65277087
  },
  "series": [
    "cae22ce1-dabe-43d1-8573-b8a8a967f75d"
  ]
}