{
  "$schema": "https://raw.githubusercontent.com/iconmaster5326/YGOJSON/main/schema/v1/card.json",
  "id": "ccec4bd2-5fa5-430a-be25-604b3c649d49",
  "text": {
    "en": {
      "name": "Vishwar Randi",
      "official": false
    },
    "de": {
      "name": "Vishwar Randi",
      "effect": "Diese Kriegerin mit ihrem unstillbaren Blutdurst ist eine Dienerin der dunklen M\u00e4chte."
    },
    "es": {
      "name": "Vishwar Randi",
      "effect": "Esta dama guerrera con insaciable deseo de sangre est\u00e1 al servicio de las fuerzas del mal."
    },
    "fr": {
      "name": "Vishwar Randi",
      "effect": "Cette guerri\u00e8re assoiff\u00e9e de sang est au service des forces des t\u00e9n\u00e8bres."
    },
    "it": {
      "name": "Vishwar Randi",
      "effect": "L'inestinguibile sete di sangue di questa donna guerriero \u00e8 al servizio delle forze dell'Oscurit\u00e0."
    },
    "pt": {
      "name": "Vishwar Randi",
      "effect": "Essa guerreira com uma insaci\u00e1vel sede de sangue serve \u00e0s for\u00e7as das trevas."
    },
    "ja": {
      "name": "\u30f4\u30a3\u30b7\u30e5\u30ef\u30fb\u30e9\u30f3\u30c7\u30a3\u30fc",
      "effect": "\u95c7\u306b\u4ed5\u3048\u308b\u5973\u6226\u58eb\u3002\u76f8\u624b\u3092\u8840\u796d\u308a\u306b\u3042\u3052\u308b\u3053\u3068\u304c\u751f\u304d\u304c\u3044\u3002"
    },
    "ko": {
      "name": "\ube44\uc288\uc640 \ub780\ub514",
      "effect": "\uc5b4\ub460\uc744 \uc12c\uae30\ub294 \uc5ec\uc804\uc0ac. \uc0c1\ub300\ub97c \uc81c\ubb3c\ub85c \ubc14\uce58\ub294 \uac83\uc774 \uc0b6\uc758 \ubcf4\ub78c."
    },
    "zh-TW": {
      "name": "\u5973\u591c\u9b54\u6230\u58eb",
      "effect": "\u4f8d\u5949\u9ed1\u6697\u7684\u5973\u6230\u58eb\u3002\u751f\u5b58\u76ee\u7684\u5c31\u662f\u8840\u796d\u5c0d\u624b\u3002"
    },
    "zh-CN": {
      "name": "\u5973\u591c\u9b54\u6218\u58eb",
      "effect": "\u4f8d\u5949\u9ed1\u6697\u7684\u5973\u6218\u58eb\u3002\u5c06\u5bf9\u65b9\u8fdb\u884c\u8840\u796d\u662f\u5979\u751f\u5b58\u7684\u610f\u4e49\u3002"
    }
  },
  "cardType": "monster",
  "attribute": "dark",
  "type": "warrior",
  "classifications": [
    "normal"
  ],
  "level": 3,
  "atk": 900,
  "def": 700,
  "passwords": [
    "78556320"
  ],
  "images": [
    {
      "id": "7596aeed-8432-4332-a438-c221cf1f7c39",
      "password": "78556320",
      "art": "https://images.ygoprodeck.com/images/cards_cropped/78556320.jpg",
      "card": "https://images.ygoprodeck.com/images/cards/78556320.jpg"
    }
  ],
  "sets": [
    "961bdd75-4ac9-406c-a5dc-9562834c5ba0",
    "211dac86-dc1a-4753-8690-a7001d0d8226"
  ],
  "legality": {
    "ocg": {
      "current": "unlimited"
    }
  },
  "masterDuel": {
    "rarity": "n",
    "craftable": true
  },
  "duelLinks": {
    "rarity": "n"
  },
  "externalIDs": {
    "yugipedia": [
      {
        "name": "Vishwar Randi",
        "id": 6365
      }
    ],
    "dbID": 4245,
    "ygoprodeck": {
      "id": 78556320,
      "name": "vishwar-randi-6597"
    },
    "yamlyugiID": 78556320
  },
  "series": []
}