{
  "$schema": "https://raw.githubusercontent.com/iconmaster5326/YGOJSON/main/schema/v1/set.json",
  "id": "0ab33a82-e535-48b7-9a99-6bba7f225f5d",
  "name": {
    "en": "Creation Pack 04 +1 Bonus Pack"
  },
  "locales": {
    "ae": {
      "language": "ae",
      "prefix": "CR04-AES",
      "date": "2024-04-27",
      "cardImages": {
        "unlimited": {}
      },
      "formats": [
        "ocg"
      ],
      "editions": [
        "unlimited"
      ],
      "externalIDs": {}
    }
  },
  "contents": [
    {
      "locales": [
        "ae"
      ],
      "formats": [
        "ocg"
      ],
      "editions": [
        "unlimited"
      ],
      "cards": [
        {
          "id": "b1b15072-c5ef-4194-94a0-6a6e515da5b3",
          "card": "44d56350-dc2c-4969-bfa7-bc52de2b8184",
          "suffix": "08",
          "rarity": "ultra"
        },
        {
          "id": "fad2c777-4536-4f5c-82c7-f8cbb1df92c3",
          "card": "e34d8547-6e13-42e8-b1f5-197dcf0c54d0",
          "suffix": "16",
          "rarity": "ultra"
        },
        {
          "id": "d2998b42-f437-4300-9b4e-3fb5f38fcba5",
          "card": "e34d8547-6e13-42e8-b1f5-197dcf0c54d0",
          "suffix": "16",
          "rarity": "25thsecret"
        },
        {
          "id": "89ddf607-6294-4cbd-b160-b05bab06349d",
          "card": "b3483033-fc12-42ec-86b5-9743379b3445",
          "suffix": "17",
          "rarity": "ultra"
        },
        {
          "id": "6f958c54-4f37-45d4-8511-e70f5e17c1fa",
          "card": "9d9c6317-6a35-4959-99a5-249c17485d37",
          "suffix": "20",
          "rarity": "secret"
        },
        {
          "id": "1542d4a3-9d4e-45b6-918f-3549959335ae",
          "card": "40b6585c-718b-4b6f-91aa-5be0e4270771",
          "suffix": "01",
          "rarity": "25thsecret"
        }
      ],
      "externalIDs": {}
    }
  ],
  "externalIDs": {
    "yugipedia": {
      "name": "Creation Pack 04 +1 Bonus Pack",
      "id": 1052962
    }
  }
}