{
  "$schema": "https://raw.githubusercontent.com/iconmaster5326/YGOJSON/main/schema/v1/set.json",
  "id": "312866d8-30d5-4657-90a8-ec1adfba8be6",
  "name": {
    "en": "Yu-Gi-Oh! World Championship 2011 prize cards"
  },
  "locales": {
    "en": {
      "language": "en",
      "date": "2011-08-14",
      "cardImages": {
        "unlimited": {}
      },
      "formats": [
        "tcg"
      ],
      "editions": [
        "unlimited"
      ],
      "externalIDs": {
        "dbIDs": [
          1121210008
        ]
      }
    },
    "ae": {
      "language": "ae",
      "date": "2011-08-14",
      "image": "https://ms.yugipedia.com//2/20/Asian.png",
      "cardImages": {
        "unlimited": {}
      },
      "formats": [
        "ocg"
      ],
      "editions": [
        "unlimited"
      ],
      "externalIDs": {
        "dbIDs": [
          131313002
        ]
      }
    }
  },
  "contents": [
    {
      "locales": [
        "en"
      ],
      "formats": [
        "tcg"
      ],
      "distrobution": "preconstructed",
      "editions": [
        "unlimited"
      ],
      "cards": [],
      "externalIDs": {}
    },
    {
      "locales": [
        "ae"
      ],
      "formats": [
        "ocg"
      ],
      "distrobution": "preconstructed",
      "editions": [
        "unlimited"
      ],
      "image": "https://ms.yugipedia.com//2/20/Asian.png",
      "cards": [],
      "externalIDs": {}
    }
  ],
  "externalIDs": {
    "yugipedia": {
      "name": "Yu-Gi-Oh! World Championship 2011 prize cards",
      "id": 332101
    }
  }
}