{
  "$schema": "https://raw.githubusercontent.com/iconmaster5326/YGOJSON/main/schema/v1/set.json",
  "id": "35703306-e1a5-46ea-a328-81beecb60f14",
  "name": {
    "en": "Complete Duel Set: Dragonmaid",
    "zh-CN": "\u51b3\u6597\u4e07\u5168\u5957\u7ec4 \u9f99\u5973\u4ec6"
  },
  "locales": {
    "sc": {
      "language": "zh-CN",
      "prefix": "WT01-SC",
      "date": "2025-01-18",
      "image": "https://ms.yugipedia.com//archive/0/0f/20241225195740%21WT01-PromoSC.png",
      "cardImages": {
        "unlimited": {}
      },
      "formats": [
        "ocg"
      ],
      "editions": [
        "unlimited"
      ],
      "externalIDs": {
        "dbIDs": [
          3000001441000
        ]
      }
    }
  },
  "contents": [
    {
      "locales": [
        "sc"
      ],
      "formats": [
        "ocg"
      ],
      "editions": [
        "unlimited"
      ],
      "image": "https://ms.yugipedia.com//archive/0/0f/20241225195740%21WT01-PromoSC.png",
      "cards": [
        {
          "id": "09690c0f-5ad0-4c40-b4a7-63e6b0d519fe",
          "card": "f552cf0e-232c-4873-b909-e1f7456a2834",
          "suffix": "S06",
          "rarity": "25thsecret"
        },
        {
          "id": "f33dac50-a72a-4301-a9d7-7fef8e5a2583",
          "card": "e33c0fd3-8e9e-4378-90be-b6fe145ee306",
          "suffix": "004",
          "rarity": "ultra"
        },
        {
          "id": "4d4ddd3c-15d5-47fc-8ef9-74c56f5c8598",
          "card": "f552cf0e-232c-4873-b909-e1f7456a2834",
          "suffix": "011",
          "rarity": "ultra"
        }
      ],
      "externalIDs": {}
    }
  ],
  "externalIDs": {
    "yugipedia": {
      "name": "Complete Duel Set: Dragonmaid",
      "id": 1104779
    }
  }
}