{
  "$schema": "https://raw.githubusercontent.com/iconmaster5326/YGOJSON/main/schema/v1/set.json",
  "id": "75938c82-9909-4cc8-8b32-53f16c370c55",
  "name": {
    "en": "Yu-Gi-Oh! Power of Chaos: Yugi the Destiny Limited Collector's Edition",
    "fr": "Yu-Gi-Oh! Power of Chaos: Yugi the Destiny \u00c9dition Collector limit\u00e9e",
    "de": "Yu-Gi-Oh! Power of Chaos: Yugi the Destiny Limited Collector's Edition",
    "it": "Yu-Gi-Oh! Power of Chaos: Yugi the Destiny Edizione Limitata per Collezionisti",
    "es": "Yu-Gi-Oh! Power of Chaos: Yugi the Destiny Limited Collector's Edition"
  },
  "locales": {
    "de": {
      "language": "de",
      "prefix": "PCY-G",
      "image": "https://ms.yugipedia.com//1/16/PCY-VideoGameDE-CollectorsEdition.png",
      "cardImages": {
        "unlimited": {}
      },
      "formats": [
        "tcg"
      ],
      "editions": [
        "unlimited"
      ],
      "externalIDs": {
        "dbIDs": [
          2141401001
        ]
      }
    },
    "it": {
      "language": "it",
      "prefix": "PCY-I",
      "cardImages": {
        "unlimited": {}
      },
      "formats": [
        "tcg"
      ],
      "editions": [
        "unlimited"
      ],
      "externalIDs": {
        "dbIDs": [
          4141401002
        ]
      }
    },
    "na": {
      "language": "en",
      "prefix": "PCY-",
      "image": "https://ms.yugipedia.com//b/b1/PCY-VideoGameNA-CollectorsEdition.png",
      "cardImages": {
        "unlimited": {
          "b2ccd27d-19e3-450f-9db3-b286cd0646e5": "https://ms.yugipedia.com//d/d9/AntiSpellFragrance-PCY-NA-PScR-UE.png"
        }
      },
      "formats": [
        "tcg"
      ],
      "editions": [
        "unlimited"
      ],
      "externalIDs": {
        "dbIDs": [
          1141402004
        ]
      }
    },
    "sp": {
      "language": "es",
      "prefix": "PCY-S",
      "image": "https://ms.yugipedia.com//0/05/PCY-VideoGameSP-CollectorsEdition.png",
      "cardImages": {
        "unlimited": {}
      },
      "formats": [
        "tcg"
      ],
      "editions": [
        "unlimited"
      ],
      "externalIDs": {
        "dbIDs": [
          5141401000
        ]
      }
    },
    "fr": {
      "language": "fr",
      "prefix": "PCY-F",
      "image": "https://ms.yugipedia.com//8/8e/PCY-VideoGameFR-CollectorsEdition.png",
      "cardImages": {
        "unlimited": {}
      },
      "formats": [
        "tcg"
      ],
      "editions": [
        "unlimited"
      ],
      "externalIDs": {
        "dbIDs": [
          3141401001
        ]
      }
    },
    "eu": {
      "language": "en",
      "prefix": "PCY-E",
      "date": "2003-11-28",
      "image": "https://ms.yugipedia.com//2/25/PCY-VideoGameEU-CollectorsEdition.png",
      "cardImages": {
        "unlimited": {}
      },
      "formats": [
        "tcg"
      ],
      "editions": [
        "unlimited"
      ],
      "externalIDs": {
        "dbIDs": [
          1141402004
        ]
      }
    }
  },
  "contents": [
    {
      "locales": [
        "de"
      ],
      "formats": [
        "tcg"
      ],
      "distrobution": "preconstructed",
      "editions": [
        "unlimited"
      ],
      "image": "https://ms.yugipedia.com//1/16/PCY-VideoGameDE-CollectorsEdition.png",
      "cards": [
        {
          "id": "b2ccd27d-19e3-450f-9db3-b286cd0646e5",
          "card": "0f8b0095-ab13-4946-94ca-f4af4ff308b5",
          "suffix": "002",
          "rarity": "prismaticsecret"
        }
      ],
      "externalIDs": {}
    },
    {
      "locales": [
        "it"
      ],
      "formats": [
        "tcg"
      ],
      "distrobution": "preconstructed",
      "editions": [
        "unlimited"
      ],
      "cards": [
        {
          "id": "b2ccd27d-19e3-450f-9db3-b286cd0646e5",
          "card": "0f8b0095-ab13-4946-94ca-f4af4ff308b5",
          "suffix": "002",
          "rarity": "prismaticsecret"
        }
      ],
      "externalIDs": {}
    },
    {
      "locales": [
        "na"
      ],
      "formats": [
        "tcg"
      ],
      "distrobution": "preconstructed",
      "editions": [
        "unlimited"
      ],
      "image": "https://ms.yugipedia.com//b/b1/PCY-VideoGameNA-CollectorsEdition.png",
      "cards": [
        {
          "id": "b2ccd27d-19e3-450f-9db3-b286cd0646e5",
          "card": "0f8b0095-ab13-4946-94ca-f4af4ff308b5",
          "suffix": "002",
          "rarity": "prismaticsecret"
        }
      ],
      "externalIDs": {}
    },
    {
      "locales": [
        "sp"
      ],
      "formats": [
        "tcg"
      ],
      "distrobution": "preconstructed",
      "editions": [
        "unlimited"
      ],
      "image": "https://ms.yugipedia.com//0/05/PCY-VideoGameSP-CollectorsEdition.png",
      "cards": [
        {
          "id": "b2ccd27d-19e3-450f-9db3-b286cd0646e5",
          "card": "0f8b0095-ab13-4946-94ca-f4af4ff308b5",
          "suffix": "002",
          "rarity": "prismaticsecret"
        }
      ],
      "externalIDs": {}
    },
    {
      "locales": [
        "fr"
      ],
      "formats": [
        "tcg"
      ],
      "distrobution": "preconstructed",
      "editions": [
        "unlimited"
      ],
      "image": "https://ms.yugipedia.com//8/8e/PCY-VideoGameFR-CollectorsEdition.png",
      "cards": [
        {
          "id": "b2ccd27d-19e3-450f-9db3-b286cd0646e5",
          "card": "0f8b0095-ab13-4946-94ca-f4af4ff308b5",
          "suffix": "002",
          "rarity": "prismaticsecret"
        }
      ],
      "externalIDs": {}
    },
    {
      "locales": [
        "eu"
      ],
      "formats": [
        "tcg"
      ],
      "distrobution": "preconstructed",
      "editions": [
        "unlimited"
      ],
      "image": "https://ms.yugipedia.com//2/25/PCY-VideoGameEU-CollectorsEdition.png",
      "cards": [
        {
          "id": "b2ccd27d-19e3-450f-9db3-b286cd0646e5",
          "card": "0f8b0095-ab13-4946-94ca-f4af4ff308b5",
          "suffix": "002",
          "rarity": "prismaticsecret"
        }
      ],
      "externalIDs": {}
    }
  ],
  "externalIDs": {
    "yugipedia": {
      "name": "Yu-Gi-Oh! Power of Chaos: Yugi the Destiny Limited Collector's Edition",
      "id": 700992
    }
  }
}