{
  "$schema": "https://raw.githubusercontent.com/iconmaster5326/YGOJSON/main/schema/v1/set.json",
  "id": "88410085-2222-4e34-ab32-c207a3f47bdc",
  "name": {
    "en": "Premium Pack 11",
    "ja": "\uff30\uff32\uff25\uff2d\uff29\uff35\uff2d \uff30\uff21\uff23\uff2b \uff11\uff11"
  },
  "locales": {
    "jp": {
      "language": "ja",
      "prefix": "PP11-JP",
      "date": "2007-12-22",
      "image": "https://ms.yugipedia.com//0/0b/PP11-BoosterJP.jpg",
      "cardImages": {
        "unlimited": {
          "a29a4157-59c0-4318-9ac6-7b5963746bbf": "https://ms.yugipedia.com//f/f6/ValhallaHalloftheFallen-PP11-JP-ScR.jpg"
        }
      },
      "formats": [
        "ocg"
      ],
      "editions": [
        "unlimited"
      ],
      "externalIDs": {
        "dbIDs": [
          3308010
        ]
      }
    }
  },
  "contents": [
    {
      "locales": [
        "jp"
      ],
      "formats": [
        "ocg"
      ],
      "editions": [
        "unlimited"
      ],
      "image": "https://ms.yugipedia.com//0/0b/PP11-BoosterJP.jpg",
      "cards": [
        {
          "id": "a29a4157-59c0-4318-9ac6-7b5963746bbf",
          "card": "fec799d9-b1a6-4651-a8ed-bd14d133b374",
          "suffix": "008",
          "rarity": "secret"
        }
      ],
      "externalIDs": {}
    }
  ],
  "externalIDs": {
    "yugipedia": {
      "name": "Premium Pack 11",
      "id": 76056
    }
  }
}