{
  "$schema": "https://raw.githubusercontent.com/iconmaster5326/YGOJSON/main/schema/v1/set.json",
  "id": "895ce716-c595-4d88-a7da-ee98a58c7102",
  "name": {
    "en": "Yu-Gi-Oh! WORLD CHAMPIONSHIP 2007 Bundles",
    "fr": "Yu-Gi-Oh! WORLD CHAMPIONSHIP 2007 Jeux",
    "de": "Yu-Gi-Oh! WORLD CHAMPIONSHIP 2007 Pakete",
    "it": "Yu-Gi-Oh! WORLD CHAMPIONSHIP 2007 Bundle",
    "es": "Yu-Gi-Oh! WORLD CHAMPIONSHIP 2007 Videojuegos",
    "ja": "\u904a\u622f\u738b\u30c7\u30e5\u30a8\u30eb\u30e2\u30f3\u30b9\u30bf\u30fc\u30ba \ufeff\uff37\uff2f\uff32\uff2c\uff24 \uff23\uff28\uff21\uff2d\uff30\uff29\uff2f\uff2e\uff33\uff28\uff29\uff30 \uff12\uff10\uff10\uff17 \u540c\u68b1\u30ab\u30fc\u30c9"
  },
  "locales": {
    "sp": {
      "language": "es",
      "prefix": "WC07-SP",
      "cardImages": {
        "unlimited": {
          "3035e706-77df-40e1-bba4-7fee2d5876bb": "https://ms.yugipedia.com//4/49/SpellStriker-WC07-SP-SR-UE.png",
          "c239ddc9-33cf-40ec-9d2e-f37a9ed45649": "https://ms.yugipedia.com//d/d6/ExploderDragon-WC07-SP-SR-UE.png",
          "0adfddec-ef38-4c8d-82bb-a88b759aee7a": "https://ms.yugipedia.com//d/d0/DestinyHERODiskCommander-WC07-SP-SR-UE.jpg"
        }
      },
      "formats": [
        "tcg"
      ],
      "editions": [
        "unlimited"
      ],
      "externalIDs": {
        "dbIDs": [
          5141405002
        ]
      }
    },
    "en": {
      "language": "en",
      "prefix": "WC07-EN",
      "date": "2007-03-20",
      "image": "https://ms.yugipedia.com//b/ba/WC07-VideoGame-NA.jpg",
      "cardImages": {
        "unlimited": {
          "3035e706-77df-40e1-bba4-7fee2d5876bb": "https://ms.yugipedia.com//f/fb/SpellStriker-WC07-EN-SR-UE.jpg",
          "c239ddc9-33cf-40ec-9d2e-f37a9ed45649": "https://ms.yugipedia.com//1/10/ExploderDragon-WC07-EN-SR-UE.jpg",
          "0adfddec-ef38-4c8d-82bb-a88b759aee7a": "https://ms.yugipedia.com//8/8b/DestinyHERODiskCommander-WC07-EN-SR-UE.jpg"
        }
      },
      "formats": [
        "tcg"
      ],
      "editions": [
        "unlimited"
      ],
      "externalIDs": {
        "dbIDs": [
          1141406001
        ]
      }
    },
    "de": {
      "language": "de",
      "prefix": "WC07-DE",
      "cardImages": {
        "unlimited": {
          "3035e706-77df-40e1-bba4-7fee2d5876bb": "https://ms.yugipedia.com//3/3a/SpellStriker-WC07-DE-SR-UE.png",
          "c239ddc9-33cf-40ec-9d2e-f37a9ed45649": "https://ms.yugipedia.com//2/20/ExploderDragon-WC07-DE-SR-UE.png",
          "0adfddec-ef38-4c8d-82bb-a88b759aee7a": "https://ms.yugipedia.com//e/e1/DestinyHERODiskCommander-WC07-DE-SR-UE.png"
        }
      },
      "formats": [
        "tcg"
      ],
      "editions": [
        "unlimited"
      ],
      "externalIDs": {
        "dbIDs": [
          2141405002
        ]
      }
    },
    "fr": {
      "language": "fr",
      "prefix": "WC07-FR",
      "image": "https://ms.yugipedia.com//8/83/WC07-VideoGameFR.jpg",
      "cardImages": {
        "unlimited": {
          "3035e706-77df-40e1-bba4-7fee2d5876bb": "https://ms.yugipedia.com//f/f5/SpellStriker-WC07-FR-SR-UE.jpg",
          "c239ddc9-33cf-40ec-9d2e-f37a9ed45649": "https://ms.yugipedia.com//1/11/ExploderDragon-WC07-FR-SR-UE.png",
          "0adfddec-ef38-4c8d-82bb-a88b759aee7a": "https://ms.yugipedia.com//9/90/DestinyHERODiskCommander-WC07-FR-SR-UE.jpg"
        }
      },
      "formats": [
        "tcg"
      ],
      "editions": [
        "unlimited"
      ],
      "externalIDs": {
        "dbIDs": [
          3141405002
        ]
      }
    },
    "it": {
      "language": "it",
      "prefix": "WC07-IT",
      "cardImages": {
        "unlimited": {
          "3035e706-77df-40e1-bba4-7fee2d5876bb": "https://ms.yugipedia.com//2/25/SpellStriker-WC07-IT-SR-UE.png",
          "c239ddc9-33cf-40ec-9d2e-f37a9ed45649": "https://ms.yugipedia.com//3/30/ExploderDragon-WC07-IT-SR-UE.png",
          "0adfddec-ef38-4c8d-82bb-a88b759aee7a": "https://ms.yugipedia.com//6/6b/DestinyHERODiskCommander-WC07-IT-SR-UE.png"
        }
      },
      "formats": [
        "tcg"
      ],
      "editions": [
        "unlimited"
      ],
      "externalIDs": {
        "dbIDs": [
          4141405002
        ]
      }
    },
    "jp": {
      "language": "ja",
      "prefix": "WC07-JP",
      "date": "2007-03-15",
      "image": "https://ms.yugipedia.com//f/f1/WC07-VideoGameJP.jpg",
      "cardImages": {
        "unlimited": {
          "fec13f96-e0d3-4f64-b01b-b24bf5d01979": "https://ms.yugipedia.com//6/66/SpellStriker-WC07-JP-UR.jpg",
          "a32e2eba-8442-4051-a872-f4d9d5bc9ef1": "https://ms.yugipedia.com//8/84/ExploderDragon-WC07-JP-UR.jpg",
          "c20010b4-4e17-4f8a-bc00-33da43f3378b": "https://ms.yugipedia.com//f/fb/DestinyHERODiskCommander-WC07-JP-UR.jpg"
        }
      },
      "formats": [
        "ocg"
      ],
      "editions": [
        "unlimited"
      ],
      "externalIDs": {
        "dbIDs": [
          151508002
        ]
      }
    }
  },
  "contents": [
    {
      "locales": [
        "sp"
      ],
      "formats": [
        "tcg"
      ],
      "distrobution": "preconstructed",
      "editions": [
        "unlimited"
      ],
      "cards": [
        {
          "id": "3035e706-77df-40e1-bba4-7fee2d5876bb",
          "card": "98fc5390-8fb6-4eb2-b08d-127e65c46e13",
          "suffix": "001",
          "rarity": "super"
        },
        {
          "id": "c239ddc9-33cf-40ec-9d2e-f37a9ed45649",
          "card": "414e7226-a3a8-4462-8a26-b195fbdd3678",
          "suffix": "002",
          "rarity": "super"
        },
        {
          "id": "0adfddec-ef38-4c8d-82bb-a88b759aee7a",
          "card": "1d0f1703-675e-4e6c-b56b-99da34cc8633",
          "suffix": "003",
          "rarity": "super"
        }
      ],
      "externalIDs": {}
    },
    {
      "locales": [
        "en"
      ],
      "formats": [
        "tcg"
      ],
      "distrobution": "preconstructed",
      "editions": [
        "unlimited"
      ],
      "image": "https://ms.yugipedia.com//b/ba/WC07-VideoGame-NA.jpg",
      "cards": [
        {
          "id": "3035e706-77df-40e1-bba4-7fee2d5876bb",
          "card": "98fc5390-8fb6-4eb2-b08d-127e65c46e13",
          "suffix": "001",
          "rarity": "super"
        },
        {
          "id": "c239ddc9-33cf-40ec-9d2e-f37a9ed45649",
          "card": "414e7226-a3a8-4462-8a26-b195fbdd3678",
          "suffix": "002",
          "rarity": "super"
        },
        {
          "id": "0adfddec-ef38-4c8d-82bb-a88b759aee7a",
          "card": "1d0f1703-675e-4e6c-b56b-99da34cc8633",
          "suffix": "003",
          "rarity": "super"
        }
      ],
      "externalIDs": {}
    },
    {
      "locales": [
        "de"
      ],
      "formats": [
        "tcg"
      ],
      "distrobution": "preconstructed",
      "editions": [
        "unlimited"
      ],
      "cards": [
        {
          "id": "3035e706-77df-40e1-bba4-7fee2d5876bb",
          "card": "98fc5390-8fb6-4eb2-b08d-127e65c46e13",
          "suffix": "001",
          "rarity": "super"
        },
        {
          "id": "c239ddc9-33cf-40ec-9d2e-f37a9ed45649",
          "card": "414e7226-a3a8-4462-8a26-b195fbdd3678",
          "suffix": "002",
          "rarity": "super"
        },
        {
          "id": "0adfddec-ef38-4c8d-82bb-a88b759aee7a",
          "card": "1d0f1703-675e-4e6c-b56b-99da34cc8633",
          "suffix": "003",
          "rarity": "super"
        }
      ],
      "externalIDs": {}
    },
    {
      "locales": [
        "fr"
      ],
      "formats": [
        "tcg"
      ],
      "distrobution": "preconstructed",
      "editions": [
        "unlimited"
      ],
      "image": "https://ms.yugipedia.com//8/83/WC07-VideoGameFR.jpg",
      "cards": [
        {
          "id": "3035e706-77df-40e1-bba4-7fee2d5876bb",
          "card": "98fc5390-8fb6-4eb2-b08d-127e65c46e13",
          "suffix": "001",
          "rarity": "super"
        },
        {
          "id": "c239ddc9-33cf-40ec-9d2e-f37a9ed45649",
          "card": "414e7226-a3a8-4462-8a26-b195fbdd3678",
          "suffix": "002",
          "rarity": "super"
        },
        {
          "id": "0adfddec-ef38-4c8d-82bb-a88b759aee7a",
          "card": "1d0f1703-675e-4e6c-b56b-99da34cc8633",
          "suffix": "003",
          "rarity": "super"
        }
      ],
      "externalIDs": {}
    },
    {
      "locales": [
        "it"
      ],
      "formats": [
        "tcg"
      ],
      "distrobution": "preconstructed",
      "editions": [
        "unlimited"
      ],
      "cards": [
        {
          "id": "3035e706-77df-40e1-bba4-7fee2d5876bb",
          "card": "98fc5390-8fb6-4eb2-b08d-127e65c46e13",
          "suffix": "001",
          "rarity": "super"
        },
        {
          "id": "c239ddc9-33cf-40ec-9d2e-f37a9ed45649",
          "card": "414e7226-a3a8-4462-8a26-b195fbdd3678",
          "suffix": "002",
          "rarity": "super"
        },
        {
          "id": "0adfddec-ef38-4c8d-82bb-a88b759aee7a",
          "card": "1d0f1703-675e-4e6c-b56b-99da34cc8633",
          "suffix": "003",
          "rarity": "super"
        }
      ],
      "externalIDs": {}
    },
    {
      "locales": [
        "jp"
      ],
      "formats": [
        "ocg"
      ],
      "distrobution": "preconstructed",
      "editions": [
        "unlimited"
      ],
      "image": "https://ms.yugipedia.com//f/f1/WC07-VideoGameJP.jpg",
      "cards": [
        {
          "id": "fec13f96-e0d3-4f64-b01b-b24bf5d01979",
          "card": "98fc5390-8fb6-4eb2-b08d-127e65c46e13",
          "suffix": "001",
          "rarity": "ultra"
        },
        {
          "id": "a32e2eba-8442-4051-a872-f4d9d5bc9ef1",
          "card": "414e7226-a3a8-4462-8a26-b195fbdd3678",
          "suffix": "002",
          "rarity": "ultra"
        },
        {
          "id": "c20010b4-4e17-4f8a-bc00-33da43f3378b",
          "card": "1d0f1703-675e-4e6c-b56b-99da34cc8633",
          "suffix": "003",
          "rarity": "ultra"
        }
      ],
      "externalIDs": {}
    }
  ],
  "externalIDs": {
    "yugipedia": {
      "name": "Yu-Gi-Oh! World Championship 2007 promotional cards",
      "id": 19820
    }
  }
}