{
  "$schema": "https://raw.githubusercontent.com/iconmaster5326/YGOJSON/main/schema/v1/set.json",
  "id": "a007a823-cbf2-43c8-aa75-ed54d9b9ad4b",
  "name": {
    "en": "Dimension Box Limited Edition",
    "ja": "\u30c7\u30a3\u30e1\u30f3\u30b7\u30e7\u30f3\u30dc\u30c3\u30af\u30b9 \uff0d\u30ea\u30df\u30c6\u30c3\u30c9\u30fb\u30a8\u30c7\u30a3\u30b7\u30e7\u30f3\uff0d",
    "ko": "\uff24\uff29\uff2d\uff25\uff2e\uff33\uff29\uff2f\uff2e  \uff33\uff25\uff34"
  },
  "locales": {
    "jp": {
      "language": "ja",
      "prefix": "DBLE-JP",
      "date": "2016-11-26",
      "image": "https://ms.yugipedia.com//3/35/DBLE-DeckJP.png",
      "cardImages": {
        "unlimited": {
          "196d9130-b051-485d-b8c7-dd5e81fff469": "https://ms.yugipedia.com//0/0f/OddEyesPendulumDragon-DBLE-JP-EScPR.png",
          "9683d198-48f0-41ca-9866-8fa9b32d0d60": "https://ms.yugipedia.com//f/f1/Predaplast-DBLE-JP-UPR.png",
          "3423b5a1-754e-4c81-889d-c334960e5eff": "https://ms.yugipedia.com//d/d9/HotRedDragonArchfiendKingCalamity-DBLE-JP-NPR.png",
          "caa7c942-6f8b-4f1c-becc-a5a6c77cc41c": "https://ms.yugipedia.com//2/25/GalaxyEyesPhotonDragon-DBLE-JP-NPR.png"
        }
      },
      "formats": [
        "ocg"
      ],
      "editions": [
        "unlimited"
      ],
      "externalIDs": {
        "dbIDs": [
          111117000
        ]
      }
    },
    "kr": {
      "language": "ko",
      "prefix": "DBLE-KR",
      "date": "2017-01-20",
      "image": "https://ms.yugipedia.com//4/4a/DBLE-DeckKR.png",
      "cardImages": {
        "1st": {
          "896b5e90-d724-4cca-b48f-f116b7561343": "https://ms.yugipedia.com//3/31/Predaplast-DBLE-KR-UPR-1E.png",
          "d8f09d31-1907-429d-bb1b-9178db0b776d": "https://ms.yugipedia.com//f/ff/HotRedDragonArchfiendKingCalamity-DBLE-KR-NPR-1E.png",
          "2aaa17c9-aeca-41f7-9fa2-ec206d9a09ad": "https://ms.yugipedia.com//9/97/GalaxyEyesPhotonDragon-DBLE-KR-NPR-1E.png"
        },
        "limited": {
          "fd03ef6d-5c23-415e-8358-4b677f994fdf": "https://ms.yugipedia.com//5/5c/OddEyesPendulumDragon-DBLE-KR-EScPR-LE.png"
        }
      },
      "formats": [
        "ocg"
      ],
      "editions": [
        "1st",
        "limited"
      ],
      "externalIDs": {
        "dbIDs": [
          74412000
        ]
      }
    }
  },
  "contents": [
    {
      "locales": [
        "jp"
      ],
      "formats": [
        "ocg"
      ],
      "editions": [
        "unlimited"
      ],
      "image": "https://ms.yugipedia.com//3/35/DBLE-DeckJP.png",
      "cards": [
        {
          "id": "196d9130-b051-485d-b8c7-dd5e81fff469",
          "card": "3aea8beb-b860-4b89-bb58-2b56ab9bfc32",
          "suffix": "S01",
          "rarity": "extrasecretparallel"
        },
        {
          "id": "9683d198-48f0-41ca-9866-8fa9b32d0d60",
          "card": "d9fee886-d06c-4b82-ab77-5d58efc39ef6",
          "suffix": "005",
          "rarity": "ultraparallel"
        },
        {
          "id": "3423b5a1-754e-4c81-889d-c334960e5eff",
          "card": "5e177af7-c587-4e40-b91a-7669922008fe",
          "suffix": "039",
          "rarity": "commonparallel"
        },
        {
          "id": "caa7c942-6f8b-4f1c-becc-a5a6c77cc41c",
          "card": "5f925c26-760d-46c2-ba6e-f796f9047471",
          "suffix": "040",
          "rarity": "commonparallel"
        }
      ],
      "externalIDs": {}
    },
    {
      "locales": [
        "kr"
      ],
      "formats": [
        "ocg"
      ],
      "editions": [
        "1st",
        "limited"
      ],
      "image": "https://ms.yugipedia.com//4/4a/DBLE-DeckKR.png",
      "cards": [
        {
          "id": "fd03ef6d-5c23-415e-8358-4b677f994fdf",
          "card": "3aea8beb-b860-4b89-bb58-2b56ab9bfc32",
          "suffix": "S01",
          "rarity": "extrasecretparallel"
        },
        {
          "id": "896b5e90-d724-4cca-b48f-f116b7561343",
          "card": "d9fee886-d06c-4b82-ab77-5d58efc39ef6",
          "suffix": "005",
          "rarity": "ultraparallel"
        },
        {
          "id": "d8f09d31-1907-429d-bb1b-9178db0b776d",
          "card": "5e177af7-c587-4e40-b91a-7669922008fe",
          "suffix": "039",
          "rarity": "commonparallel"
        },
        {
          "id": "2aaa17c9-aeca-41f7-9fa2-ec206d9a09ad",
          "card": "5f925c26-760d-46c2-ba6e-f796f9047471",
          "suffix": "040",
          "rarity": "commonparallel"
        }
      ],
      "externalIDs": {}
    }
  ],
  "externalIDs": {
    "yugipedia": {
      "name": "Dimension Box Limited Edition",
      "id": 460575
    }
  }
}