{
  "$schema": "https://raw.githubusercontent.com/iconmaster5326/YGOJSON/main/schema/v1/set.json",
  "id": "a652257f-85bf-4b8b-8053-d3303034b574",
  "name": {
    "en": "OTS Tournament Pack 26",
    "fr": "OTS Pack de Tournoi 26",
    "de": "OTS Tournament Pack 26",
    "it": "OTS Buste da Torneo 26",
    "pt": "OTS Pacote de Torneio 26",
    "es": "OTS Sobre Torneo 26"
  },
  "locales": {
    "sp": {
      "language": "es",
      "cardImages": {},
      "formats": [
        "tcg"
      ],
      "externalIDs": {}
    },
    "en": {
      "language": "en",
      "prefix": "OP26-EN",
      "image": "https://ms.yugipedia.com//6/60/OP26-BoosterEN.png",
      "cardImages": {
        "unlimited": {}
      },
      "formats": [
        "tcg"
      ],
      "editions": [
        "unlimited"
      ],
      "externalIDs": {}
    },
    "de": {
      "language": "de",
      "cardImages": {},
      "formats": [
        "tcg"
      ],
      "externalIDs": {}
    },
    "fr": {
      "language": "fr",
      "cardImages": {},
      "formats": [
        "tcg"
      ],
      "externalIDs": {}
    },
    "it": {
      "language": "it",
      "cardImages": {},
      "formats": [
        "tcg"
      ],
      "externalIDs": {}
    },
    "pt": {
      "language": "pt",
      "date": "2024-10-17",
      "cardImages": {},
      "formats": [
        "tcg"
      ],
      "externalIDs": {}
    }
  },
  "contents": [
    {
      "locales": [
        "sp"
      ],
      "formats": [
        "tcg"
      ],
      "cards": [],
      "externalIDs": {}
    },
    {
      "locales": [
        "en"
      ],
      "formats": [
        "tcg"
      ],
      "editions": [
        "unlimited"
      ],
      "image": "https://ms.yugipedia.com//6/60/OP26-BoosterEN.png",
      "cards": [
        {
          "id": "112447e6-08de-48b6-aadf-2579f7ec73a8",
          "card": "f4c5992e-0324-4d7f-8c19-f7da2a298bc3",
          "suffix": "0??",
          "rarity": "ultimate"
        }
      ],
      "externalIDs": {}
    },
    {
      "locales": [
        "de"
      ],
      "formats": [
        "tcg"
      ],
      "cards": [],
      "externalIDs": {}
    },
    {
      "locales": [
        "fr"
      ],
      "formats": [
        "tcg"
      ],
      "cards": [],
      "externalIDs": {}
    },
    {
      "locales": [
        "it"
      ],
      "formats": [
        "tcg"
      ],
      "cards": [],
      "externalIDs": {}
    },
    {
      "locales": [
        "pt"
      ],
      "formats": [
        "tcg"
      ],
      "cards": [],
      "externalIDs": {}
    }
  ],
  "externalIDs": {
    "yugipedia": {
      "name": "OTS Tournament Pack 26",
      "id": 1063002
    }
  }
}