{
  "$schema": "https://raw.githubusercontent.com/iconmaster5326/YGOJSON/main/schema/v1/set.json",
  "id": "b0f28e3d-b93f-42f7-9518-5a27b9304349",
  "date": "2024-05-17",
  "name": {
    "en": "Rush Selection BOX Vol.01"
  },
  "contents": [
    {
      "formats": [
        "duellinks"
      ],
      "image": "https://ms.yugipedia.com//2/29/RushSelectionBOXVol01.png",
      "cards": [],
      "externalIDs": {}
    }
  ],
  "externalIDs": {
    "yugipedia": {
      "name": "Rush Selection BOX Vol.01",
      "id": 1059563
    }
  }
}