{
  "$schema": "https://raw.githubusercontent.com/iconmaster5326/YGOJSON/main/schema/v1/set.json",
  "id": "faded2f4-4667-4d21-8241-953b1a8854ce",
  "name": {
    "en": "Structure Deck: Shaddoll Showdown",
    "fr": "Deck de Structure : La Confrontation des Marionnettes de l'Ombre",
    "de": "Structure Deck: Shaddoll Showdown",
    "it": "Structure Deck: Resa dei Conti Bambolaombra",
    "pt": "Deck Estrutural: Confronto Sombraneco",
    "es": "Baraja de Estructura: Confrontaci\u00f3n de Sombra\u00f1ecas"
  },
  "locales": {
    "pt": {
      "language": "pt",
      "prefix": "SDSH-PT",
      "date": "2020-02-13",
      "cardImages": {
        "1st": {}
      },
      "formats": [
        "tcg"
      ],
      "editions": [
        "1st"
      ],
      "externalIDs": {}
    },
    "sp": {
      "language": "es",
      "prefix": "SDSH-SP",
      "image": "https://ms.yugipedia.com//4/4f/SDSH-DeckSP.png",
      "cardImages": {
        "1st": {}
      },
      "formats": [
        "tcg"
      ],
      "editions": [
        "1st"
      ],
      "externalIDs": {}
    },
    "en": {
      "language": "en",
      "prefix": "SDSH-EN",
      "image": "https://ms.yugipedia.com//5/5c/SDSH-DeckEN.png",
      "cardImages": {
        "1st": {
          "46db852b-4e4a-43f6-b75f-40d090b349cd": "https://ms.yugipedia.com//4/4f/QadshaddollKeios-SDSH-EN-SR-1E.png",
          "9539223a-8d26-41cc-94af-db8dd4fea2a3": "https://ms.yugipedia.com//3/34/ShaddollHedgehog-SDSH-EN-C-1E.png",
          "fe302c32-912e-45da-a063-2c57adb16632": "https://ms.yugipedia.com//2/2d/BlackLusterSoldierEnvoyoftheBeginning-SDSH-EN-C-1E.png",
          "31b78f3d-052f-4a97-81c6-ec6aa6cf66c5": "https://ms.yugipedia.com//7/78/SinisterShadowGames-SDSH-EN-C-1E.png",
          "5c1e0cbb-3e3c-4197-9d1d-1b23c7a6fc43": "https://ms.yugipedia.com//5/54/ShaddollConstruct-SDSH-EN-C-1E.png",
          "87cc0614-9532-4a78-982b-048de64ae74c": "https://ms.yugipedia.com//2/2b/ElShaddollConstruct-SDSH-EN-UR-1E.png"
        }
      },
      "formats": [
        "tcg"
      ],
      "editions": [
        "1st"
      ],
      "externalIDs": {
        "dbIDs": [
          14415003
        ]
      }
    },
    "fr": {
      "language": "fr",
      "prefix": "SDSH-FR",
      "image": "https://ms.yugipedia.com//0/08/SDSH-DeckFR.png",
      "cardImages": {
        "1st": {}
      },
      "formats": [
        "tcg"
      ],
      "editions": [
        "1st"
      ],
      "externalIDs": {}
    },
    "it": {
      "language": "it",
      "prefix": "SDSH-IT",
      "image": "https://ms.yugipedia.com//6/6c/SDSH-DeckIT.png",
      "cardImages": {
        "1st": {}
      },
      "formats": [
        "tcg"
      ],
      "editions": [
        "1st"
      ],
      "externalIDs": {}
    },
    "de": {
      "language": "de",
      "prefix": "SDSH-DE",
      "image": "https://ms.yugipedia.com//1/1d/SDSH-DeckDE.png",
      "cardImages": {
        "1st": {}
      },
      "formats": [
        "tcg"
      ],
      "editions": [
        "1st"
      ],
      "externalIDs": {}
    }
  },
  "contents": [
    {
      "locales": [
        "pt"
      ],
      "formats": [
        "tcg"
      ],
      "editions": [
        "1st"
      ],
      "cards": [
        {
          "id": "da01f1e1-fc58-443b-8d95-e100649c8702",
          "card": "c9f71ead-8315-456a-a3b8-04c040c74071",
          "suffix": "001",
          "rarity": "super"
        },
        {
          "id": "9539223a-8d26-41cc-94af-db8dd4fea2a3",
          "card": "e1158757-54a5-4aa1-a8f3-d2bee3e80ef6",
          "suffix": "005",
          "rarity": "common"
        },
        {
          "id": "613645cf-3416-41c1-9eda-af9eae7bb28c",
          "card": "0626cd7e-9544-4a18-8625-85b0ac76bb54",
          "suffix": "012",
          "rarity": "common"
        },
        {
          "id": "f998c885-c9aa-4390-8ab5-aa1e856cd843",
          "card": "0ee31411-884b-4179-b39a-5bbff1ee953c",
          "suffix": "035",
          "rarity": "common"
        },
        {
          "id": "0707be60-b391-4952-821c-fa2272c0310b",
          "card": "6ba39d45-1266-452b-b943-d7c43e6c6ad5",
          "suffix": "044",
          "rarity": "common"
        },
        {
          "id": "17cd60bf-87c2-4c4c-8820-855a796a8b4a",
          "card": "e0e73bd4-640a-4487-87af-a063577ac953",
          "suffix": "046",
          "rarity": "ultra"
        }
      ],
      "externalIDs": {}
    },
    {
      "locales": [
        "sp"
      ],
      "formats": [
        "tcg"
      ],
      "editions": [
        "1st"
      ],
      "image": "https://ms.yugipedia.com//4/4f/SDSH-DeckSP.png",
      "cards": [
        {
          "id": "bea9915c-658a-43d4-96df-6e2362217675",
          "card": "c9f71ead-8315-456a-a3b8-04c040c74071",
          "suffix": "001",
          "rarity": "super"
        },
        {
          "id": "9539223a-8d26-41cc-94af-db8dd4fea2a3",
          "card": "e1158757-54a5-4aa1-a8f3-d2bee3e80ef6",
          "suffix": "005",
          "rarity": "common"
        },
        {
          "id": "8d1a0a6a-4c69-4594-b077-61c38171a2a5",
          "card": "0626cd7e-9544-4a18-8625-85b0ac76bb54",
          "suffix": "012",
          "rarity": "common"
        },
        {
          "id": "2a3e8397-b6bb-4bd9-b5e1-65f189e86b67",
          "card": "0ee31411-884b-4179-b39a-5bbff1ee953c",
          "suffix": "035",
          "rarity": "common"
        },
        {
          "id": "ff05a35a-5a00-49df-ad01-b7cd7d495b07",
          "card": "6ba39d45-1266-452b-b943-d7c43e6c6ad5",
          "suffix": "044",
          "rarity": "common"
        },
        {
          "id": "0cc0347b-0c80-4bd6-9147-fc7a74d3c647",
          "card": "e0e73bd4-640a-4487-87af-a063577ac953",
          "suffix": "046",
          "rarity": "ultra"
        }
      ],
      "externalIDs": {}
    },
    {
      "locales": [
        "en"
      ],
      "formats": [
        "tcg"
      ],
      "editions": [
        "1st"
      ],
      "image": "https://ms.yugipedia.com//5/5c/SDSH-DeckEN.png",
      "cards": [
        {
          "id": "46db852b-4e4a-43f6-b75f-40d090b349cd",
          "card": "c9f71ead-8315-456a-a3b8-04c040c74071",
          "suffix": "001",
          "rarity": "super"
        },
        {
          "id": "9539223a-8d26-41cc-94af-db8dd4fea2a3",
          "card": "e1158757-54a5-4aa1-a8f3-d2bee3e80ef6",
          "suffix": "005",
          "rarity": "common"
        },
        {
          "id": "fe302c32-912e-45da-a063-2c57adb16632",
          "card": "0626cd7e-9544-4a18-8625-85b0ac76bb54",
          "suffix": "012",
          "rarity": "common"
        },
        {
          "id": "31b78f3d-052f-4a97-81c6-ec6aa6cf66c5",
          "card": "0ee31411-884b-4179-b39a-5bbff1ee953c",
          "suffix": "035",
          "rarity": "common"
        },
        {
          "id": "5c1e0cbb-3e3c-4197-9d1d-1b23c7a6fc43",
          "card": "6ba39d45-1266-452b-b943-d7c43e6c6ad5",
          "suffix": "044",
          "rarity": "common"
        },
        {
          "id": "87cc0614-9532-4a78-982b-048de64ae74c",
          "card": "e0e73bd4-640a-4487-87af-a063577ac953",
          "suffix": "046",
          "rarity": "ultra"
        }
      ],
      "externalIDs": {}
    },
    {
      "locales": [
        "fr"
      ],
      "formats": [
        "tcg"
      ],
      "editions": [
        "1st"
      ],
      "image": "https://ms.yugipedia.com//0/08/SDSH-DeckFR.png",
      "cards": [
        {
          "id": "2461d633-7bdc-4339-be41-e9299e3aa8cb",
          "card": "c9f71ead-8315-456a-a3b8-04c040c74071",
          "suffix": "001",
          "rarity": "super"
        },
        {
          "id": "9539223a-8d26-41cc-94af-db8dd4fea2a3",
          "card": "e1158757-54a5-4aa1-a8f3-d2bee3e80ef6",
          "suffix": "005",
          "rarity": "common"
        },
        {
          "id": "583c9745-4f36-45d9-9104-0735c483b391",
          "card": "0626cd7e-9544-4a18-8625-85b0ac76bb54",
          "suffix": "012",
          "rarity": "common"
        },
        {
          "id": "8262da44-d0d2-4971-8d72-075aa85664ec",
          "card": "0ee31411-884b-4179-b39a-5bbff1ee953c",
          "suffix": "035",
          "rarity": "common"
        },
        {
          "id": "85cd511d-5ecd-4402-acd0-b002aed3a7d5",
          "card": "6ba39d45-1266-452b-b943-d7c43e6c6ad5",
          "suffix": "044",
          "rarity": "common"
        },
        {
          "id": "48117a4e-eade-41b0-a0bc-a980bd669a58",
          "card": "e0e73bd4-640a-4487-87af-a063577ac953",
          "suffix": "046",
          "rarity": "ultra"
        }
      ],
      "externalIDs": {}
    },
    {
      "locales": [
        "it"
      ],
      "formats": [
        "tcg"
      ],
      "editions": [
        "1st"
      ],
      "image": "https://ms.yugipedia.com//6/6c/SDSH-DeckIT.png",
      "cards": [
        {
          "id": "c70775ae-4019-44e6-9280-7e385407c5a8",
          "card": "c9f71ead-8315-456a-a3b8-04c040c74071",
          "suffix": "001",
          "rarity": "super"
        },
        {
          "id": "9539223a-8d26-41cc-94af-db8dd4fea2a3",
          "card": "e1158757-54a5-4aa1-a8f3-d2bee3e80ef6",
          "suffix": "005",
          "rarity": "common"
        },
        {
          "id": "02089550-b616-4d5a-8e8d-a11a90551aa7",
          "card": "0626cd7e-9544-4a18-8625-85b0ac76bb54",
          "suffix": "012",
          "rarity": "common"
        },
        {
          "id": "60b41ac9-8dca-40fb-876f-4228be085161",
          "card": "0ee31411-884b-4179-b39a-5bbff1ee953c",
          "suffix": "035",
          "rarity": "common"
        },
        {
          "id": "2cc81571-3811-49a8-a5ba-d9821a8fe9ea",
          "card": "6ba39d45-1266-452b-b943-d7c43e6c6ad5",
          "suffix": "044",
          "rarity": "common"
        },
        {
          "id": "50ef984f-277e-4a4d-880a-6cccecfc22b3",
          "card": "e0e73bd4-640a-4487-87af-a063577ac953",
          "suffix": "046",
          "rarity": "ultra"
        }
      ],
      "externalIDs": {}
    },
    {
      "locales": [
        "de"
      ],
      "formats": [
        "tcg"
      ],
      "editions": [
        "1st"
      ],
      "image": "https://ms.yugipedia.com//1/1d/SDSH-DeckDE.png",
      "cards": [
        {
          "id": "167cfb65-22e0-4ee6-b765-37a110d22416",
          "card": "c9f71ead-8315-456a-a3b8-04c040c74071",
          "suffix": "001",
          "rarity": "super"
        },
        {
          "id": "9539223a-8d26-41cc-94af-db8dd4fea2a3",
          "card": "e1158757-54a5-4aa1-a8f3-d2bee3e80ef6",
          "suffix": "005",
          "rarity": "common"
        },
        {
          "id": "226d45d4-b04d-4d22-92de-f5c31861c464",
          "card": "0626cd7e-9544-4a18-8625-85b0ac76bb54",
          "suffix": "012",
          "rarity": "common"
        },
        {
          "id": "71c9dd20-2795-4c46-bea7-4d8bee1d6053",
          "card": "0ee31411-884b-4179-b39a-5bbff1ee953c",
          "suffix": "035",
          "rarity": "common"
        },
        {
          "id": "c0ee0c6f-227b-47dc-af51-11e79936d161",
          "card": "6ba39d45-1266-452b-b943-d7c43e6c6ad5",
          "suffix": "044",
          "rarity": "common"
        },
        {
          "id": "d3f74fbe-5238-4c31-a99e-cb67ac8d8118",
          "card": "e0e73bd4-640a-4487-87af-a063577ac953",
          "suffix": "046",
          "rarity": "ultra"
        }
      ],
      "externalIDs": {}
    }
  ],
  "externalIDs": {
    "yugipedia": {
      "name": "Structure Deck: Shaddoll Showdown",
      "id": 677417
    }
  }
}