{
  "$schema": "https://json-schema.org/draft/2020-12/schema",
  "$id": "https://raw.githubusercontent.com/iconmaster5326/YGOJSON/main/schema/v1/rarity.json",
  "title": "Card Rarity",

  "description": "A card's rarity. This enum uses the TCG name of a rarity where possible, but is used for both the TCG and OCG version of the rarity.",
  "enum": [
    "common",
    "shortprint",
    "rare",
    "super",
    "ultra",
    "ultimate",
    "secret",
    "ultrasecret",
    "prismaticsecret",
    "ghost",
    "parallel",
    "commonparallel",
    "rareparallel",
    "superparallel",
    "ultraparallel",
    "dtpc",
    "dtpsp",
    "dtrpr",
    "dtspr",
    "dtupr",
    "dtscpr",
    "gold",
    "10000secret",
    "20thsecret",
    "collectors",
    "extrasecret",
    "extrasecretparallel",
    "goldghost",
    "goldsecret",
    "starfoil",
    "mosaic",
    "shatterfoil",
    "ghostparallel",
    "platinum",
    "platinumsecret",
    "premiumgold",
    "25thsecret",
    "secretparallel",
    "starlight",
    "pharaohs",
    "kccommon",
    "kcrare",
    "kcsuper",
    "kcultra",
    "kcsecret",
    "millenium",
    "milleniumsuper",
    "milleniumultra",
    "milleniumsecret",
    "milleniumgold"
  ]
}
