{
  "id": "7451a380-8f2d-4430-bf97-8fd23a2fcc8b",
  "name": {
    "en": "Ancient Gear Golem",
    "de": "Antiker Antriebsgolem",
    "es": "Golem de Mecanismo Antiguo",
    "fr": "Golem Rouages Ancients",
    "it": "Golem-Ingranaggio Antico",
    "pt": "Golem do Mecanismo Antigo",
    "ja": "\u30a2\u30f3\u30c6\u30a3\u30fc\u30af\u30fb\u30ae\u30a2\u30b4\u30fc\u30ec\u30e0",
    "ja_romaji": "Ant\u012bku Giag\u014dremu",
    "ko": "\uc564\ud2f1 \uae30\uc5b4 \uace8\ub818"
  },
  "archetype": true,
  "members": [
    "12f92d5c-a473-4e59-931a-18e583f69a18",
    "25825678-751f-47f9-bb83-f15616caf94f",
    "e648c88f-e2fa-4bac-8a2d-d87a64130434"
  ],
  "externalIDs": {
    "yugipedia": {
      "name": "Ancient Gear Golem (archetype)",
      "id": 987229
    }
  }
}