{
  "id": "87cf5bca-ace5-4a65-a6b3-baad66bd1236",
  "name": {
    "en": "Celtic Guard",
    "de": "Keltisch",
    "es": "Celta",
    "fr": "Celt",
    "it": "Celtico",
    "pt": "Celta",
    "ja": "\u30a8\u30eb\u30d5\u306e\u5263\u58eb",
    "ja_romaji": "Erufu no Kenshi",
    "ko": "\uc5d8\ud504 \uac80\uc0ac",
    "ko_rr": "Elpeu Geomsa",
    "zh-TW": "\u7cbe\u9748\u528d\u58eb"
  },
  "archetype": true,
  "members": [
    "57bbd53d-3856-45c1-8474-1498c17020ce",
    "a67cdc23-1c24-4efd-926e-a34f249d130a",
    "e003193d-d3f4-46ed-b9c7-c4e0cc9ad559"
  ],
  "externalIDs": {
    "yugipedia": {
      "name": "Celtic Guard",
      "id": 362324
    }
  }
}